<?xml version='1.0' encoding='UTF-8'?>
<titlepatch status="alive" titleid="BLJM60567"><tag name="BLJM60567_T4" popup="true" signoff="true"><package version="01.03" size="22069472" sha1sum="e88d734eca36c1bc5eac52c4bb4efdb2af8daaba" url="http://b0.ww.np.dl.playstation.net/tppkg/np/BLJM60567/BLJM60567_T4/696a31156f0f293a/JP0102-BLJM60567_00-VAMPIRE000000002-A0103-V0100-PE.pkg" ps3_system_ver="04.2000"><paramsfo><TITLE>ヴァンパイア リザレクション</TITLE><TITLE_00>ヴァンパイア リザレクション</TITLE_00><TITLE_01>Vampire Resurrection</TITLE_01><TITLE_02>Vampire Resurrection</TITLE_02><TITLE_03>Vampire Resurrection</TITLE_03><TITLE_04>Vampire Resurrection</TITLE_04><TITLE_05>Vampire Resurrection</TITLE_05></paramsfo></package></tag></titlepatch>