<?xml version='1.0' encoding='UTF-8'?>
<titlepatch status="alive" titleid="NPJB00366"><tag name="NPJB00366_T4" popup="true" signoff="true"><package version="01.01" size="374194128" sha1sum="238d513ae50e6a8320f10cac7c142b691142bf65" url="http://b0.ww.np.dl.playstation.net/tppkg/np/NPJB00366/NPJB00366_T4/c74661881eaa9a23/JP0036-NPJB00366_00-CHAOSCODEPS3JPXX-A0101-V0100-PE.pkg" ps3_system_ver="04.2000"><paramsfo><TITLE>Chaos Code</TITLE><TITLE_10>Chaos Code</TITLE_10></paramsfo></package></tag></titlepatch>