<?xml version='1.0' encoding='UTF-8'?>
<titlepatch status="alive" titleid="BLUS31445"><tag name="BLUS31445_T10" popup="true" signoff="true"><package version="01.07" size="724881280" sha1sum="0080fa3374e097325ce21ae5d9eeee7e8ccaa566" url="http://b0.ww.np.dl.playstation.net/tppkg/np/BLUS31445/BLUS31445_T10/ff82027770648db7/UP1001-BLUS31445_00-BLPRESEQUELPATCH-A0107-V0100-PE.pkg" ps3_system_ver="04.5000"><paramsfo><TITLE>Borderlands: The Pre-Sequel Additional Content</TITLE><TITLE_01>Borderlands: The Pre-Sequel
Additional Content</TITLE_01><TITLE_02>Borderlands: The Pre-Sequel
Contenu additionnel</TITLE_02><TITLE_03>Borderlands: The Pre-Sequel
Contenido adicional</TITLE_03><TITLE_04>Borderlands: The Pre-Sequel
Zusätzliche Inhalte</TITLE_04><TITLE_05>Borderlands: The Pre-Sequel
Contenuto Aggiuntivo</TITLE_05></paramsfo></package></tag></titlepatch>