<?xml version='1.0' encoding='UTF-8'?>
<titlepatch status="alive" titleid="BCUS98298"><tag name="BCUS98298_T2" popup="true" signoff="true"><package version="01.01" size="87937536" sha1sum="3a75cdd94a81b191bd1938d53ae15312d6696583" url="http://b0.ww.np.dl.playstation.net/tppkg/np/BCUS98298/BCUS98298_T2/fa5fe7942dad5b82/UP9000-BCUS98298_00-PATCH00000000001-A0101-V0100-PE.pkg" ps3_system_ver="04.4000"/><package version="01.02" size="49493984" sha1sum="5ff653bf72941665325b0578374d81122b09cb40" url="http://b0.ww.np.dl.playstation.net/tppkg/np/BCUS98298/BCUS98298_T2/fa5fe7942dad5b82/UP9000-BCUS98298_00-PATCH00000000002-A0102-V0100-PE.pkg" ps3_system_ver="04.4000"><paramsfo><TITLE>Beyond: Two Souls™ Update Data (US)</TITLE><TITLE_00>Beyond: Two Souls™ アップデートデータ (US)</TITLE_00><TITLE_01>Beyond: Two Souls™ Update Data (US)</TITLE_01><TITLE_02>Beyond: Two Souls™ - Mise à jour des données (US)</TITLE_02><TITLE_03>Beyond: Two Souls™ Datos de actualización (US)</TITLE_03><TITLE_04>Beyond: Two Souls™ Update Daten (US)</TITLE_04><TITLE_05>Beyond: Two Souls™ Aggiornamento dati (US)</TITLE_05><TITLE_06>Beyond: Two Souls™ Update Data (US)</TITLE_06><TITLE_07>Beyond: Two Souls™ Conteúdo de atualização (US)</TITLE_07><TITLE_08>Beyond: Two Souls™ обновленные данные (US)</TITLE_08><TITLE_09>Beyond: Two Souls™ 업데이트 데이터 (US)</TITLE_09><TITLE_10>Beyond: Two Souls™ 更新資料 (US)</TITLE_10><TITLE_11>Beyond: Two Souls™ 更新資料 (US)</TITLE_11><TITLE_12>Beyond: Two Souls™  Päivitysten tiedot (US)</TITLE_12><TITLE_13>Beyond: Two Souls™ Uppdateringsdata (US)</TITLE_13><TITLE_14>Beyond: Two Souls™ Opdateret indhold (US)</TITLE_14><TITLE_15>Beyond: Two Souls™ oppdatert innhold (US)</TITLE_15><TITLE_16>Beyond: Two Souls™ Dane aktualizacji (US)</TITLE_16></paramsfo></package></tag></titlepatch>