<?xml version='1.0' encoding='UTF-8'?>
<titlepatch status="alive" titleid="BCES01594"><tag name="BCES01594_T4" popup="true" signoff="true"><package version="01.04" size="447204752" sha1sum="857a2858c32c9cd78e1ccd969fe6425c09d2cdc0" url="http://b0.ww.np.dl.playstation.net/tppkg/np/BCES01594/BCES01594_T4/0f99e3776b5bdf07/EP9000-BCES01594_00-RATCHETQFORCE001-A0104-V0100-PE.pkg" ps3_system_ver="04.3000"/><package version="01.05" size="451932976" sha1sum="72b900ba4987c5a56366492165b098ca85611169" url="http://b0.ww.np.dl.playstation.net/tppkg/np/BCES01594/BCES01594_T4/0f99e3776b5bdf07/EP9000-BCES01594_00-RATCHETQFORCE001-A0105-V0100-PE.pkg" ps3_system_ver="04.3000"><paramsfo><TITLE>Ratchet &amp; Clank™: QForce (EU) Install Data</TITLE><TITLE_02>Données d'installation de Ratchet &amp; Clank™: QForce (EU)</TITLE_02><TITLE_03>Datos de instalación de Ratchet &amp; Clank™: QForce (EU)</TITLE_03><TITLE_04>"Ratchet &amp; Clank™: QForce (EU)"-Installationsdaten </TITLE_04><TITLE_05>Dati installazione di Ratchet &amp; Clank™: QForce (EU)</TITLE_05><TITLE_06>Installatiedata Ratchet &amp; Clank™: QForce (EU)</TITLE_06><TITLE_07>Dados de instalaçao de Ratchet &amp; Clank™: QForce (EU)</TITLE_07><TITLE_12>Ratchet &amp; Clank™: QForce (EU) -asennustiedot</TITLE_12><TITLE_13>Ratchet &amp; Clank™: Qforce (EU) installationsdata</TITLE_13><TITLE_14>Installeringsdata til Ratchet &amp; Clank™: QForce (EU)</TITLE_14><TITLE_15>Ratchet &amp; Clank™: QForce (EU) -installeringsdata</TITLE_15><TITLE_16>Dane instalacji Ratchet &amp; Clank™: Załoga Q (EU)</TITLE_16></paramsfo></package></tag></titlepatch>