<?xml version='1.0' encoding='UTF-8'?>
<titlepatch status="alive" titleid="NPUB30018"><tag name="NPUB30018_T3" popup="true" signoff="true"><package version="02.01" size="133639216" sha1sum="06e1f5a2b9862f0954e59174574d023f75c661dc" url="http://b0.ww.np.dl.playstation.net/tppkg/np/NPUB30018/NPUB30018_T3/7414d155ec8883bd/UP0102-NPUB30018_00-000000000000DEMO-A0201-V0200-PE.pkg" ps3_system_ver="01.9200"><paramsfo><TITLE>Rocketmen: Axis of Evil</TITLE><TITLE_01>Rocketmen: Axis of Evil</TITLE_01><TITLE_02>Rocketmen: Axis of Evil</TITLE_02><TITLE_03>Rocketmen: Axis of Evil</TITLE_03><TITLE_04>Rocketmen: Axis of Evil</TITLE_04><TITLE_05>Rocketmen: Axis of Evil</TITLE_05></paramsfo></package></tag></titlepatch>