<?xml version='1.0' encoding='UTF-8'?>
<titlepatch status="alive" titleid="NPJA00030"><tag name="NPJA00030_T0" popup="true" signoff="true"><package version="01.10" size="6548400" sha1sum="91e862341aad9b4f0d0a380f35d6ce0b7db4cc0b" url="http://b0.ww.np.dl.playstation.net/tppkg/np/NPJA00030/NPJA00030_T0/b674d136423fda2c/JP9000-NPJA00030_00-ELEFUNKPATCH0110-A0110-V0100-PE.pkg" ps3_system_ver="02.3000"><paramsfo><TITLE>エレファンク™</TITLE><TITLE_00>エレファンク™</TITLE_00><TITLE_01>エレファンク™</TITLE_01></paramsfo></package></tag></titlepatch>